Workbook

Sheet Dashboard
A1: 🏥 MEDICAL STORE MANAGEMENT SYSTEM | PHARMA DASHBOARD
A4: Real-time Inventory · Sales · Expiry · Credit Tracking
A5: KEY PERFORMANCE INDICATORS
A6: 💰 TODAY'S SALES (PKR) | D6: 📅 MONTHLY SALES (PKR) | G6: 📈 GROSS PROFIT (PKR) | J6: 📦 INVENTORY VALUE (PKR) | M6: 💳 TOTAL CREDIT DUE (PKR) | P6: ⚠ EXPIRING SOON (Items) | S6: 🔴 LOW STOCK (Items)
A7: =IFERROR(SUMIF(Sales_Entry!C:C,TODAY(),Sales_Entry!I:I),0) -> 0 | D7: =IFERROR(SUMPRODUCT((MONTH(Sales_Entry!C2:C101)=MONTH(TODAY()))*(YEAR(Sales_Entry!C2:C101)=YEAR(TODAY()))*Sales_Entry!I2:I101),0) -> 18375 | G7: =IFERROR(SUM(Sales_Entry!L2:L101),0) -> 140182 | J7: =IFERROR(SUMPRODUCT(Inventory_Status!H2:H101,Inventory_Status!D2:D101),0) -> 1776045 | M7: =IFERROR(SUMIF(Sales_Entry!M:M,"Credit",Sales_Entry!O:O),0) -> 62578 | P7: =IFERROR(COUNTIFS(Expiry_Alert!G3:G102,"URGENT")+COUNTIFS(Expiry_Alert!G3:G102,"EXPIRED"),0) -> 13 | S7: =IFERROR(COUNTIF(Low_Stock_Alert!H3:H102,"HIGH")+COUNTIF(Low_Stock_Alert!H3:H102,"CRITICAL"),0) -> 19

Sheet Financial Summary
A1: FINANCIAL SUMMARY
A2: Total Purchases (PKR) | K2: =IFERROR(SUM(Purchase_Entry!H2:H101),0) -> 1625768
A3: Total Revenue (PKR) | K3: =IFERROR(SUM(Sales_Entry!I2:I101),0) -> 272789
A4: Total Cost of Goods | K4: =IFERROR(SUM(Sales_Entry!K2:K101),0) -> 132607
A5: Gross Profit (PKR) | K5: =IFERROR(SUM(Sales_Entry!L2:L101),0) -> 140182
A6: Profit Margin % | K6: =IFERROR(SUM(Sales_Entry!L2:L101)/SUM(Sales_Entry!I2:I101),0) -> 0.51388436
A7: Cash Sales (PKR) | K7: =IFERROR(SUMIF(Sales_Entry!M:M,"Cash",Sales_Entry!I:I),0) -> 194186
A8: Credit Sales (PKR) | K8: =IFERROR(SUMIF(Sales_Entry!M:M,"Credit",Sales_Entry!I:I),0) -> 78603
A9: Credit Outstanding (PKR) | K9: =IFERROR(SUMIF(Sales_Entry!M:M,"Credit",Sales_Entry!O:O),0) -> 62578
A10: Total Medicines | K10: =COUNTA(Medicine_Master!A2:A101) -> 96
A11: Total Transactions | K11: =COUNTA(Sales_Entry!A2:A101) -> 96

Sheet Analysis
A1: Month | B1: Sum of Total_Revenue_PKR
A2: Dec 2025 | B2: 106276
A3: Feb 2026 | B3: 58172
A4: Jan 2026 | B4: 89966
A5: Mar 2026 | B5: 18375
A6: Grand Total | B6: 272789
A8: Medicine_Name | B8: Sum of Quantity
A9: Ipratropium | B9: 68
A10: Omega-3 | B10: 70
A11: Fluconazole 150mg | B11: 85
A12: Ciprofloxacin 500mg | B12: 88
A13: Azithromycin 250mg | B13: 93
A14: Pseudoephedrine | B14: 96
A15: Ketorolac 10mg | B15: 104
A16: Ranitidine 150mg | B16: 110
A17: Vitamin C 500mg | B17: 116
A18: Augmentin 625mg | B18: 135
A19: Grand Total | B19: 965
A21: Payment_Type | B21: Sum of Total_Revenue_PKR
A22: Cash | B22: 194186
A23: Credit | B23: 78603
A24: (blank)
A25: Grand Total | B25: 272789
A27: Priority | B27: Count of Medicine_Name
A28: CRITICAL | B28: 18
A29: HIGH | B29: 1
A30: MEDIUM | B30: 8
A31: OK | B31: 69
A32: Grand Total | B32: 96

Sheet Medicine_Search
B1: 🔍 MEDICINE SEARCH & LOOKUP
B3: Search by Med_ID: | C3: MED002
B4: ℹ️ Type medicine name in D4 OR Med_ID (e.g. MED016) in J4 → Results appear below automatically
B6: 📋 MEDICINE DETAILS
B7: Med_ID | C7: Medicine_Name | D7: Category | E7: Form | F7: Sale_Price_PKR | G7: Cost_Price_PKR | H7: Reorder_Level | I7: Expiry_Date | J7: Manufacturer | K7: Pack_Size | L7: Unit | M7: Status
B8: {=_xlfn._xlws.FILTER(Table2[],ISNUMBER(SEARCH(C3,Table2[Med_ID])))} -> MED002 | C8: Augmentin 625mg | D8: Antibiotics | E8: Tablet | F8: 220 | G8: 110 | H8: 50 | I8: 46386 | J8: Novartis | K8: 20 | L8: Tablets/Caps/ml | M8: Active
B9: 📦 STOCK & SALES SUMMARY
B10: Med_ID | C10: Medicine_Name | D10: Category | E10: Cost_Price_PKR | F10: Sale_Price_PKR | G10: Total_Purchased | H10: Total_Sold | I10: Current_Stock | J10: Reorder_Level | K10: Stock_Value_PKR | L10: Days_to_Expiry | M10: Expiry_Status | N10: Reorder_Needed | O10: Suggested_Order_Qty | P10: Movement_Status
B11: {=_xlfn._xlws.FILTER(Table5[],ISNUMBER(SEARCH(C3,Table5[Med_ID])))} -> MED002 | C11: Augmentin 625mg | D11: Antibiotics | E11: 110 | F11: 220 | G11: 628 | H11: 135 | I11: 493 | J11: 50 | K11: 54230 | L11: 299 | M11: OK | N11: NO | O11: 0 | P11: Active
B12: ⚠️ EXPIRY & ALERT STATUS
B13: Med_ID | C13: Medicine_Name | D13: Category | E13: Current_Stock | F13: Expiry_Date | G13: Days_Remaining | H13: Expiry_Status | I13: Cost_Price_PKR | J13: Financial_Risk_PKR
B14: {=_xlfn._xlws.FILTER(Table7[],ISNUMBER(SEARCH(C3,Table7[Med_ID])))} -> MED002 | C14: Augmentin 625mg | D14: Antibiotics | E14: 493 | F14: 46386 | G14: 299 | H14: OK | I14: 110 | J14: 54230
B15: 🧾 RECENT SALES HISTORY ( PURCHASE )
B16: Purchase_ID | C16: Date | D16: Med_ID | E16: Medicine_Name | F16: Supplier | G16: Quantity | H16: Cost_Price_PKR | I16: Total_Cost_PKR | J16: Invoice_No | K16: Batch_No | L16: Expiry_Date | M16: Payment_Status
B17: {=_xlfn._xlws.FILTER(Table3[],ISNUMBER(SEARCH(C3,Table3[Med_ID])))} -> PUR0052 | C17: 45926 | D17: MED002 | E17: Augmentin 625mg | F17: City Medical | G17: 284 | H17: 110 | I17: 31240 | J17: INV23104 | K17: B175 | L17: 46386 | M17: Paid
B18: PUR0096 | C18: 45988 | D18: MED002 | E18: Augmentin 625mg | F18: Dawa Center | G18: 344 | H18: 110 | I18: 37840 | J18: INV10772 | K18: B460 | L18: 46386 | M18: Paid
B20: 🧾 RECENT SALES HISTORY ( SALES )
B21: Sale_ID | C21: Month | D21: Date | E21: Med_ID | F21: Medicine_Name | G21: Customer_Name | H21: Quantity | I21: Sale_Price_PKR | J21: Total_Revenue_PKR | K21: Cost_Price_PKR | L21: Total_Cost_PKR | M21: Gross_Profit_PKR | N21: Payment_Type | O21: Amount_Paid | P21: Balance_Due
B22: {=_xlfn._xlws.FILTER(Table4[],ISNUMBER(SEARCH(C3,Table4[Med_ID])))} -> SAL0017 | C22: Jan 2026 | D22: 46045 | E22: MED002 | F22: Augmentin 625mg | G22: Kamran Iqbal | H22: 36 | I22: 220 | J22: 7920 | K22: 110 | L22: 3960 | M22: 3960 | N22: Cash | O22: 7920 | P22: 0
B23: SAL0043 | C23: Dec 2025 | D23: 46003 | E23: MED002 | F23: Augmentin 625mg | G23: Usman Ali | H23: 34 | I23: 220 | J23: 7480 | K23: 110 | L23: 3740 | M23: 3740 | N23: Cash | O23: 7480 | P23: 0
B24: SAL0062 | C24: Dec 2025 | D24: 46016 | E24: MED002 | F24: Augmentin 625mg | G24: Rabia Nawaz | H24: 38 | I24: 220 | J24: 8360 | K24: 110 | L24: 4180 | M24: 4180 | N24: Cash | O24: 8360 | P24: 0
B25: SAL0071 | C25: Dec 2025 | D25: 46007 | E25: MED002 | F25: Augmentin 625mg | G25: Tariq Mahmood | H25: 5 | I25: 220 | J25: 1100 | K25: 110 | L25: 550 | M25: 550 | N25: Cash | O25: 1100 | P25: 0
B26: SAL0092 | C26: Jan 2026 | D26: 46032 | E26: MED002 | F26: Augmentin 625mg | G26: Lubna Farooq | H26: 22 | I26: 220 | J26: 4840 | K26: 110 | L26: 2420 | M26: 2420 | N26: Credit | O26: 2420 | P26: 2420

Sheet Medicine_Master
A1: Med_ID | B1: Medicine_Name | C1: Category | D1: Form | E1: Sale_Price_PKR | F1: Cost_Price_PKR | G1: Reorder_Level | H1: Expiry_Date | I1: Manufacturer | J1: Pack_Size | K1: Unit | L1: Status
A2: MED001 | B2: Amoxicillin 500mg | C2: Antibiotics | D2: Capsule | E2: 45 | F2: 22 | G2: 100 | H2: 46090 | I2: Abbott | J2: 20 | K2: Tablets/Caps/ml | L2: Active
A3: MED002 | B3: Augmentin 625mg | C3: Antibiotics | D3: Tablet | E3: 220 | F3: 110 | G3: 50 | H3: 46386 | I3: Novartis | J3: 20 | K3: Tablets/Caps/ml | L3: Active
A4: MED003 | B4: Azithromycin 250mg | C4: Antibiotics | D4: Tablet | E4: 180 | F4: 88 | G4: 60 | H4: 46726 | I4: Roche | J4: 10 | K4: Tablets/Caps/ml | L4: Active
A5: MED004 | B5: Ciprofloxacin 500mg | C5: Antibiotics | D5: Tablet | E5: 95 | F5: 46 | G5: 80 | H5: 46478 | I5: Novartis | J5: 14 | K5: Tablets/Caps/ml | L5: Active
A6: MED005 | B6: Metronidazole 400mg | C6: Antibiotics | D6: Tablet | E6: 35 | F6: 17 | G6: 100 | H6: 46278 | I6: Abbott | J6: 20 | K6: Tablets/Caps/ml | L6: Active
A7: MED006 | B7: Cephalexin 500mg | C7: Antibiotics | D7: Capsule | E7: 120 | F7: 58 | G7: 60 | H7: 46117 | I7: ICI Pakistan | J7: 10 | K7: Tablets/Caps/ml | L7: Active
A8: MED007 | B8: Cephalexin 500mg | C8: Antibiotics | D8: Capsule | E8: 85 | F8: 41 | G8: 80 | H8: 46713 | I8: Novartis | J8: 20 | K8: Tablets/Caps/ml | L8: Active
A9: MED008 | B9: Paracetamol 500mg | C9: Analgesics | D9: Tablet | E9: 12 | F9: 5 | G9: 200 | H9: 46130 | I9: Bayer | J9: 20 | K9: Tablets/Caps/ml | L9: Active
A10: MED009 | B10: Ibuprofen 400mg | C10: Analgesics | D10: Tablet | E10: 28 | F10: 13 | G10: 150 | H10: 46063 | I10: GSK | J10: 14 | K10: Tablets/Caps/ml | L10: Active
A11: MED010 | B11: Diclofenac 50mg | C11: Analgesics | D11: Tablet | E11: 42 | F11: 20 | G11: 120 | H11: 46138 | I11: Pfizer | J11: 14 | K11: Tablets/Caps/ml | L11: Active
A12: MED011 | B12: Aspirin 75mg | C12: Analgesics | D12: Tablet | E12: 18 | F12: 8 | G12: 150 | H12: 46254 | I12: Sanofi | J12: 30 | K12: Tablets/Caps/ml | L12: Active
A13: MED012 | B13: Tramadol 50mg | C13: Analgesics | D13: Capsule | E13: 95 | F13: 46 | G13: 70 | H13: 46776 | I13: Ferozsons | J13: 20 | K13: Tablets/Caps/ml | L13: Active
... A97: MED096 | B97: Tacrolimus Ointment | C97: Skin Care | D97: Ointment | E97: 425 | F97: 210 | G97: 25 | H97: 46564 | I97: Ferozsons | J97: 30 | K97: Tablets/Caps/ml | L97: Active

Sheet Purchase_Entry
A1: Purchase_ID | B1: Date | C1: Med_ID | D1: Medicine_Name | E1: Supplier | F1: Quantity | G1: Cost_Price_PKR | H1: Total_Cost_PKR | I1: Invoice_No | J1: Batch_No | K1: Expiry_Date | L1: Payment_Status
A2: PUR0001 | B2: 46079 | C2: MED082 | D2: Bilastine 20mg | E2: Sind Medical Corp | F2: 107 | G2: 46 | H2: =F2*G2 -> 4922 | I2: INV42098 | J2: B328 | K2: 46434 | L2: Paid
A3: PUR0002 | B3: 45912 | C3: MED095 | D3: Clobetasol Cream | E3: National Pharma | F3: 102 | G3: 75 | H3: =F3*G3 -> 7650 | I3: INV21395 | J3: B704 | K3: 46162 | L3: Pending
A4: PUR0003 | B4: 46062 | C4: MED005 | D4: Metronidazole 400mg | E4: Lahore Pharma Dist | F4: 65 | G4: 17 | H4: =F4*G4 -> 1105 | I4: INV40495 | J4: B617 | K4: 46278 | L4: Paid
A5: PUR0004 | B5: 45919 | C5: MED072 | D5: Aluminum Hydroxide | E5: National Pharma | F5: 151 | G5: 31 | H5: =F5*G5 -> 4681 | I5: INV64987 | J5: B325 | K5: 46378 | L5: Pending
A6: PUR0005 | B6: 46084 | C6: MED076 | D6: Pioglitazone 15mg | E6: Karachi Drug House | F6: 192 | G6: 61 | H6: =F6*G6 -> 11712 | I6: INV65392 | J6: B448 | K6: 46403 | L6: Paid
A7: PUR0006 | B7: 45999 | C7: MED020 | D7: Vitamin C 500mg | E7: Ali Medical Supplies | F7: 160 | G7: 16 | H7: =F7*G7 -> 2560 | I7: INV22156 | J7: B489 | K7: 46060 | L7: Paid
A8: PUR0007 | B8: 45997 | C8: MED046 | D8: Povidone Iodine | E8: City Medical | F8: 483 | G8: 70 | H8: =F8*G8 -> 33810 | I8: INV44671 | J8: B926 | K8: 46471 | L8: Paid
A9: PUR0008 | B9: 45948 | C9: MED094 | D9: Terbinafine Cream | E9: Ali Medical Supplies | F9: 285 | G9: 70 | H9: =F9*G9 -> 19950 | I9: INV59615 | J9: B180 | K9: 46492 | L9: Paid
A10: PUR0009 | B10: 45993 | C10: MED081 | D10: Hydrochlorothiazide | E10: City Medical | F10: 366 | G10: 17 | H10: =F10*G10 -> 6222 | I10: INV35203 | J10: B821 | K10: 46572 | L10: Paid
A11: PUR0010 | B11: 46027 | C11: MED006 | D11: Cephalexin 500mg | E11: Sind Medical Corp | F11: 388 | G11: 58 | H11: =F11*G11 -> 22504 | I11: INV20458 | J11: B975 | K11: 46117 | L11: Paid
A12: PUR0011 | B12: 46014 | C12: MED013 | D12: Mefenamic Acid 500mg | E12: Dawa Center | F12: 244 | G12: 26 | H12: =F12*G12 -> 6344 | I12: INV93320 | J12: B954 | K12: 46304 | L12: Paid
A13: PUR0012 | B13: 45995 | C13: MED021 | D13: Vitamin D3 1000IU | E13: Lahore Pharma Dist | F13: 239 | G13: 31 | H13: =F13*G13 -> 7409 | I13: INV97841 | J13: B373 | K13: 46691 | L13: Paid
... A97: PUR0096 | B97: 45988 | C97: MED002 | D97: Augmentin 625mg | E97: Dawa Center | F97: 344 | G97: 110 | H97: =F97*G97 -> 37840 | I97: INV10772 | J97: B460 | K97: 46386 | L97: Paid
A201: PUR0101 | B201: 46027 | C201: MED004 | D201: Ciprofloxacin 500mg | E201: Ali Medical Supplies | F201: 306 | G201: 46 | H201: 14076 | I201: INV88569 | J201: B283 | K201: 46478 | L201: Paid
A202: PUR0102 | B202: 46044 | C202: MED010 | D202: Diclofenac 50mg | E202: Ali Medical Supplies | F202: 217 | G202: 20 | H202: 4340 | I202: INV21348 | J202: B357 | K202: 46138 | L202: Paid
A203: PUR0103 | B203: 46008 | C203: MED014 | D203: Omeprazole 20mg | E203: Sind Medical Corp | F203: 296 | G203: 31 | H203: 9176 | I203: INV21775 | J203: B738 | K203: 46196 | L203: Paid
A204: PUR0104 | B204: 46050 | C204: MED016 | D204: Ranitidine 150mg | E204: Lahore Pharma Dist | F204: 350 | G204: 18 | H204: 6300 | I204: INV90375 | J204: B702 | K204: 46117 | L204: Paid
A205: PUR0105 | B205: 45974 | C205: MED019 | D205: Esomeprazole 40mg | E205: Karachi Drug House | F205: 210 | G205: 58 | H205: 12180 | I205: INV60870 | J205: B982 | K205: 46582 | L205: Paid
A206: PUR0106 | B206: 46056 | C206: MED022 | D206: Vitamin B Complex | E206: Lahore Pharma Dist | F206: 208 | G206: 21 | H206: 4368 | I206: INV96581 | J206: B283 | K206: 46132 | L206: Paid
A207: PUR0107 | B207: 46032 | C207: MED024 | D207: Iron+Folic Acid | E207: MedLife Pharma | F207: 390 | G207: 13 | H207: 5070 | I207: INV79299 | J207: B793 | K207: 46772 | L207: Paid
A208: PUR0108 | B208: 46015 | C208: MED025 | D208: Multivitamin | E208: Karachi Drug House | F208: 144 | G208: 41 | H208: 5904 | I208: INV62772 | J208: B143 | K208: 46469 | L208: Paid
A209: PUR0109 | B209: 46004 | C209: MED027 | D209: Metformin 500mg | E209: MedLife Pharma | F209: 237 | G209: 13 | H209: 3081 | I209: INV65732 | J209: B308 | K209: 46479 | L209: Paid
A210: PUR0110 | B210: 46007 | C210: MED030 | D210: Sitagliptin 100mg | E210: MedLife Pharma | F210: 285 | G210: 140 | H210: 39900 | I210: INV70566 | J210: B631 | K210: 46529 | L210: Paid
A211: PUR0111 | B211: 45998 | C211: MED040 | D211: Loratadine 10mg | E211: Lahore Pharma Dist | F211: 201 | G211: 13 | H211: 2613 | I211: INV16726 | J211: B466 | K211: 46748 | L211: Paid
A212: PUR0112 | B212: 46048 | C212: MED042 | D212: Chlorpheniramine 4mg | E212: Ali Medical Supplies | F212: 166 | G212: 7 | H212: 1162 | I212: INV67896 | J212: B709 | K212: 46376 | L212: Paid
... A223: PUR0123 | B223: 46057 | C223: MED089 | D223: Ipratropium | E223: Ali Medical Supplies | F223: 309 | G223: 140 | H223: 43260 | I223: INV83526 | J223: B426 | K223: 46350 | L223: Paid

Sheet Sales_Entry
A1: Sale_ID | B1: Month | C1: Date | D1: Med_ID | E1: Medicine_Name | F1: Customer_Name | G1: Quantity | H1: Sale_Price_PKR | I1: Total_Revenue_PKR | J1: Cost_Price_PKR | K1: Total_Cost_PKR | L1: Gross_Profit_PKR | M1: Payment_Type | N1: Amount_Paid | O1: Balance_Due
A2: SAL0001 | B2: =TEXT(C2,"mmm yyyy") -> Mar 2026 | C2: 46086 | D2: MED042 | E2: Chlorpheniramine 4mg | F2: Usman Ali | G2: 10 | H2: 15 | I2: =G2*H2 -> 150 | J2: 7 | K2: =G2*J2 -> 70 | L2: =I2-K2 -> 80 | M2: Cash | N2: 150 | O2: =I2-N2 -> 0
A3: SAL0002 | B3: =TEXT(C3,"mmm yyyy") -> Feb 2026 | C3: 46078 | D3: MED069 | E3: Piroxicam 20mg | F3: Tariq Mahmood | G3: 7 | H3: 55 | I3: =G3*H3 -> 385 | J3: 26 | K3: =G3*J3 -> 182 | L3: =I3-K3 -> 203 | M3: Cash | N3: 385 | O3: =I3-N3 -> 0
A4: SAL0003 | B4: =TEXT(C4,"mmm yyyy") -> Jan 2026 | C4: 46032 | D4: MED028 | E4: Metformin 1000mg | F4: Usman Ali | G4: 3 | H4: 45 | I4: =G4*H4 -> 135 | J4: 21 | K4: =G4*J4 -> 63 | L4: =I4-K4 -> 72 | M4: Cash | N4: 135 | O4: =I4-N4 -> 0
A5: SAL0004 | B5: =TEXT(C5,"mmm yyyy") -> Feb 2026 | C5: 46078 | D5: MED031 | E5: Glimepiride 2mg | F5: Shahid Raza | G5: 6 | H5: 65 | I5: =G5*H5 -> 390 | J5: 31 | K5: =G5*J5 -> 186 | L5: =I5-K5 -> 204 | M5: Cash | N5: 390 | O5: =I5-N5 -> 0
A6: SAL0005 | B6: =TEXT(C6,"mmm yyyy") -> Dec 2025 | C6: 46011 | D6: MED016 | E6: Ranitidine 150mg | F6: Fatima Malik | G6: 15 | H6: 38 | I6: =G6*H6 -> 570 | J6: 18 | K6: =G6*J6 -> 270 | L6: =I6-K6 -> 300 | M6: Cash | N6: 570 | O6: =I6-N6 -> 0
A7: SAL0006 | B7: =TEXT(C7,"mmm yyyy") -> Feb 2026 | C7: 46057 | D7: MED074 | E7: Omega-3 | F7: Fatima Malik | G7: 38 | H7: 185 | I7: =G7*H7 -> 7030 | J7: 90 | K7: =G7*J7 -> 3420 | L7: =I7-K7 -> 3610 | M7: Cash | N7: 7030 | O7: =I7-N7 -> 0
A8: SAL0007 | B8: =TEXT(C8,"mmm yyyy") -> Feb 2026 | C8: 46067 | D8: MED072 | E8: Aluminum Hydroxide | F8: Alina Khan | G8: 9 | H8: 65 | I8: =G8*H8 -> 585 | J8: 31 | K8: =G8*J8 -> 279 | L8: =I8-K8 -> 306 | M8: Cash | N8: 585 | O8: =I8-N8 -> 0
A9: SAL0008 | B9: =TEXT(C9,"mmm yyyy") -> Dec 2025 | C9: 45998 | D9: MED016 | E9: Ranitidine 150mg | F9: Sara Rehman | G9: 37 | H9: 38 | I9: =G9*H9 -> 1406 | J9: 18 | K9: =G9*J9 -> 666 | L9: =I9-K9 -> 740 | M9: Cash | N9: 1406 | O9: =I9-N9 -> 0
A10: SAL0009 | B10: =TEXT(C10,"mmm yyyy") -> Feb 2026 | C10: 46061 | D10: MED014 | E10: Omeprazole 20mg | F10: Sana Butt | G10: 38 | H10: 65 | I10: =G10*H10 -> 2470 | J10: 31 | K10: =G10*J10 -> 1178 | L10: =I10-K10 -> 1292 | M10: Cash | N10: 2470 | O10: =I10-N10 -> 0
A11: SAL0010 | B11: =TEXT(C11,"mmm yyyy") -> Dec 2025 | C11: 46013 | D11: MED013 | E11: Mefenamic Acid 500mg | F11: Lubna Farooq | G11: 36 | H11: 55 | I11: =G11*H11 -> 1980 | J11: 26 | K11: =G11*J11 -> 936 | L11: =I11-K11 -> 1044 | M11: Credit | N11: 0 | O11: =I11-N11 -> 1980
A12: SAL0011 | B12: =TEXT(C12,"mmm yyyy") -> Jan 2026 | C12: 46031 | D12: MED027 | E12: Metformin 500mg | F12: Asif Mirza | G12: 32 | H12: 28 | I12: =G12*H12 -> 896 | J12: 13 | K12: =G12*J12 -> 416 | L12: =I12-K12 -> 480 | M12: Credit | N12: 448 | O12: =I12-N12 -> 448
A13: SAL0012 | B13: =TEXT(C13,"mmm yyyy") -> Feb 2026 | C13: 46054 | D13: MED075 | E13: Vitamin E 400IU | F13: Sara Rehman | G13: 30 | H13: 95 | I13: =G13*H13 -> 2850 | J13: 46 | K13: =G13*J13 -> 1380 | L13: =I13-K13 -> 1470 | M13: Cash | N13: 2850 | O13: =I13-N13 -> 0
... A97: SAL0096 | B97: =TEXT(C97,"mmm yyyy") -> Jan 2026 | C97: 46051 | D97: MED058 | E97: Betamethasone Cream | F97: Ahmed Khan | G97: 33 | H97: 125 | I97: =G97*H97 -> 4125 | J97: 61 | K97: =G97*J97 -> 2013 | L97: =I97-K97 -> 2112 | M97: Credit | N97: 2062 | O97: =I97-N97 -> 2063

Sheet Inventory_Status
A1: Med_ID | B1: Medicine_Name | C1: Category | D1: Cost_Price_PKR | E1: Sale_Price_PKR | F1: Total_Purchased | G1: Total_Sold | H1: Current_Stock | I1: Reorder_Level | J1: Stock_Value_PKR | K1: Days_to_Expiry | L1: Expiry_Status | M1: Reorder_Needed | N1: Suggested_Order_Qty | O1: Movement_Status
A2: MED001 | B2: Amoxicillin 500mg | C2: Antibiotics | D2: 22 | E2: 45 | F2: =IFERROR(SUMIF(Purchase_Entry!C:C,A2,Purchase_Entry!F:F),0) -> 927 | G2: =IFERROR(SUMIF(Sales_Entry!D:D,A2,Sales_Entry!G:G),0) -> 0 | H2: =F2-G2 -> 927 | I2: 100 | J2: =H2*D2 -> 20394 | K2: =IFERROR(Medicine_Master!H2-TODAY(),"") -> 3 | L2: =IFERROR(IF(Medicine_Master!H2<TODAY(),"EXPIRED",IF(Medicine_Master!H2-TODAY()<30,"URGENT",IF(Medicine_Master!H2-TODAY()<60,"WARNING","OK"))),"OK") -> URGENT | M2: =IF(H2<I2,"YES","NO") -> NO | N2: =IFERROR(IF(H2<I2,MAX(I2-H2,ROUNDUP(SUMIF(Sales_Entry!D:D,A2,Sales_Entry!G:G)/90*30,0)),0),0) -> 0 | O2: =IFERROR(IF(SUMIF(Sales_Entry!C:C,">="&(TODAY()-60),Sales_Entry!G:G)=0,"Slow Moving","Active"),"Active") -> Active
A3: MED002 | B3: Augmentin 625mg | C3: Antibiotics | D3: 110 | E3: 220 | F3: =IFERROR(SUMIF(Purchase_Entry!C:C,A3,Purchase_Entry!F:F),0) -> 628 | G3: =IFERROR(SUMIF(Sales_Entry!D:D,A3,Sales_Entry!G:G),0) -> 135 | H3: =F3-G3 -> 493 | I3: 50 | J3: =H3*D3 -> 54230 | K3: =IFERROR(Medicine_Master!H3-TODAY(),"") -> 299 | L3: =IFERROR(IF(Medicine_Master!H3<TODAY(),"EXPIRED",IF(Medicine_Master!H3-TODAY()<30,"URGENT",IF(Medicine_Master!H3-TODAY()<60,"WARNING","OK"))),"OK") -> OK | M3: =IF(H3<I3,"YES","NO") -> NO | N3: =IFERROR(IF(H3<I3,MAX(I3-H3,ROUNDUP(SUMIF(Sales_Entry!D:D,A3,Sales_Entry!G:G)/90*30,0)),0),0) -> 0 | O3: =IFERROR(IF(SUMIF(Sales_Entry!C:C,">="&(TODAY()-60),Sales_Entry!G:G)=0,"Slow Moving","Active"),"Active") -> Active
A4: MED003 | B4: Azithromycin 250mg | C4: Antibiotics | D4: 88 | E4: 180 | F4: =IFERROR(SUMIF(Purchase_Entry!C:C,A4,Purchase_Entry!F:F),0) -> 447 | G4: =IFERROR(SUMIF(Sales_Entry!D:D,A4,Sales_Entry!G:G),0) -> 93 | H4: =F4-G4 -> 354 | I4: 60 | J4: =H4*D4 -> 31152 | K4: =IFERROR(Medicine_Master!H4-TODAY(),"") -> 639 | L4: =IFERROR(IF(Medicine_Master!H4<TODAY(),"EXPIRED",IF(Medicine_Master!H4-TODAY()<30,"URGENT",IF(Medicine_Master!H4-TODAY()<60,"WARNING","OK"))),"OK") -> OK | M4: =IF(H4<I4,"YES","NO") -> NO | N4: =IFERROR(IF(H4<I4,MAX(I4-H4,ROUNDUP(SUMIF(Sales_Entry!D:D,A4,Sales_Entry!G:G)/90*30,0)),0),0) -> 0 | O4: =IFERROR(IF(SUMIF(Sales_Entry!C:C,">="&(TODAY()-60),Sales_Entry!G:G)=0,"Slow Moving","Active"),"Active") -> Active
A5: MED004 | B5: Ciprofloxacin 500mg | C5: Antibiotics | D5: 46 | E5: 95 | F5: =IFERROR(SUMIF(Purchase_Entry!C:C,A5,Purchase_Entry!F:F),0) -> 306 | G5: =IFERROR(SUMIF(Sales_Entry!D:D,A5,Sales_Entry!G:G),0) -> 88 | H5: =F5-G5 -> 218 | I5: 80 | J5: =H5*D5 -> 10028 | K5: =IFERROR(Medicine_Master!H5-TODAY(),"") -> 391 | L5: =IFERROR(IF(Medicine_Master!H5<TODAY(),"EXPIRED",IF(Medicine_Master!H5-TODAY()<30,"URGENT",IF(Medicine_Master!H5-TODAY()<60,"WARNING","OK"))),"OK") -> OK | M5: =IF(H5<I5,"YES","NO") -> NO | N5: =IFERROR(IF(H5<I5,MAX(I5-H5,ROUNDUP(SUMIF(Sales_Entry!D:D,A5,Sales_Entry!G:G)/90*30,0)),0),0) -> 0 | O5: =IFERROR(IF(SUMIF(Sales_Entry!C:C,">="&(TODAY()-60),Sales_Entry!G:G)=0,"Slow Moving","Active"),"Active") -> Active
A6: MED005 | B6: Metronidazole 400mg | C6: Antibiotics | D6: 17 | E6: 35 | F6: =IFERROR(SUMIF(Purchase_Entry!C:C,A6,Purchase_Entry!F:F),0) -> 65 | G6: =IFERROR(SUMIF(Sales_Entry!D:D,A6,Sales_Entry!G:G),0) -> 0 | H6: =F6-G6 -> 65 | I6: 100 | J6: =H6*D6 -> 1105 | K6: =IFERROR(Medicine_Master!H6-TODAY(),"") -> 191 | L6: =IFERROR(IF(Medicine_Master!H6<TODAY(),"EXPIRED",IF(Medicine_Master!H6-TODAY()<30,"URGENT",IF(Medicine_Master!H6-TODAY()<60,"WARNING","OK"))),"OK") -> OK | M6: =IF(H6<I6,"YES","NO") -> YES | N6: =IFERROR(IF(H6<I6,MAX(I6-H6,ROUNDUP(SUMIF(Sales_Entry!D:D,A6,Sales_Entry!G:G)/90*30,0)),0),0) -> 35 | O6: =IFERROR(IF(SUMIF(Sales_Entry!C:C,">="&(TODAY()-60),Sales_Entry!G:G)=0,"Slow Moving","Active"),"Active") -> Active
A7: MED006 | B7: Cephalexin 500mg | C7: Antibiotics | D7: 58 | E7: 120 | F7: =IFERROR(SUMIF(Purchase_Entry!C:C,A7,Purchase_Entry!F:F),0) -> 388 | G7: =IFERROR(SUMIF(Sales_Entry!D:D,A7,Sales_Entry!G:G),0) -> 0 | H7: =F7-G7 -> 388 | I7: 60 | J7: =H7*D7 -> 22504 | K7: =IFERROR(Medicine_Master!H7-TODAY(),"") -> 30 | L7: =IFERROR(IF(Medicine_Master!H7<TODAY(),"EXPIRED",IF(Medicine_Master!H7-TODAY()<30,"URGENT",IF(Medicine_Master!H7-TODAY()<60,"WARNING","OK"))),"OK") -> WARNING | M7: =IF(H7<I7,"YES","NO") -> NO | N7: =IFERROR(IF(H7<I7,MAX(I7-H7,ROUNDUP(SUMIF(Sales_Entry!D:D,A7,Sales_Entry!G:G)/90*30,0)),0),0) -> 0 | O7: =IFERROR(IF(SUMIF(Sales_Entry!C:C,">="&(TODAY()-60),Sales_Entry!G:G)=0,"Slow Moving","Active"),"Active") -> Active
A8: MED007 | B8: Doxycycline 100mg | C8: Antibiotics | D8: 41 | E8: 85 | F8: =IFERROR(SUMIF(Purchase_Entry!C:C,A8,Purchase_Entry!F:F),0) -> 0 | G8: =IFERROR(SUMIF(Sales_Entry!D:D,A8,Sales_Entry!G:G),0) -> 0 | H8: =F8-G8 -> 0 | I8: 80 | J8: =H8*D8 -> 0 | K8: =IFERROR(Medicine_Master!H8-TODAY(),"") -> 626 | L8: =IFERROR(IF(Medicine_Master!H8<TODAY(),"EXPIRED",IF(Medicine_Master!H8-TODAY()<30,"URGENT",IF(Medicine_Master!H8-TODAY()<60,"WARNING","OK"))),"OK") -> OK | M8: =IF(H8<I8,"YES","NO") -> YES | N8: =IFERROR(IF(H8<I8,MAX(I8-H8,ROUNDUP(SUMIF(Sales_Entry!D:D,A8,Sales_Entry!G:G)/90*30,0)),0),0) -> 80 | O8: =IFERROR(IF(SUMIF(Sales_Entry!C:C,">="&(TODAY()-60),Sales_Entry!G:G)=0,"Slow Moving","Active"),"Active") -> Active
A9: MED008 | B9: Paracetamol 500mg | C9: Analgesics | D9: 5 | E9: 12 | F9: =IFERROR(SUMIF(Purchase_Entry!C:C,A9,Purchase_Entry!F:F),0) -> 566 | G9: =IFERROR(SUMIF(Sales_Entry!D:D,A9,Sales_Entry!G:G),0) -> 0 | H9: =F9-G9 -> 566 | I9: 200 | J9: =H9*D9 -> 2830 | K9: =IFERROR(Medicine_Master!H9-TODAY(),"") -> 43 | L9: =IFERROR(IF(Medicine_Master!H9<TODAY(),"EXPIRED",IF(Medicine_Master!H9-TODAY()<30,"URGENT",IF(Medicine_Master!H9-TODAY()<60,"WARNING","OK"))),"OK") -> WARNING | M9: =IF(H9<I9,"YES","NO") -> NO | N9: =IFERROR(IF(H9<I9,MAX(I9-H9,ROUNDUP(SUMIF(Sales_Entry!D:D,A9,Sales_Entry!G:G)/90*30,0)),0),0) -> 0 | O9: =IFERROR(IF(SUMIF(Sales_Entry!C:C,">="&(TODAY()-60),Sales_Entry!G:G)=0,"Slow Moving","Active"),"Active") -> Active
A10: MED009 | B10: Ibuprofen 400mg | C10: Analgesics | D10: 13 | E10: 28 | F10: =IFERROR(SUMIF(Purchase_Entry!C:C,A10,Purchase_Entry!F:F),0) -> 439 | G10: =IFERROR(SUMIF(Sales_Entry!D:D,A10,Sales_Entry!G:G),0) -> 6 | H10: =F10-G10 -> 433 | I10: 150 | J10: =H10*D10 -> 5629 | K10: =IFERROR(Medicine_Master!H10-TODAY(),"") -> -24 | L10: =IFERROR(IF(Medicine_Master!H10<TODAY(),"EXPIRED",IF(Medicine_Master!H10-TODAY()<30,"URGENT",IF(Medicine_Master!H10-TODAY()<60,"WARNING","OK"))),"OK") -> EXPIRED | M10: =IF(H10<I10,"YES","NO") -> NO | N10: =IFERROR(IF(H10<I10,MAX(I10-H10,ROUNDUP(SUMIF(Sales_Entry!D:D,A10,Sales_Entry!G:G)/90*30,0)),0),0) -> 0 | O10: =IFERROR(IF(SUMIF(Sales_Entry!C:C,">="&(TODAY()-60),Sales_Entry!G:G)=0,"Slow Moving","Active"),"Active") -> Active
A11: MED010 | B11: Diclofenac 50mg | C11: Analgesics | D11: 20 | E11: 42 | F11: =IFERROR(SUMIF(Purchase_Entry!C:C,A11,Purchase_Entry!F:F),0) -> 217 | G11: =IFERROR(SUMIF(Sales_Entry!D:D,A11,Sales_Entry!G:G),0) -> 8 | H11: =F11-G11 -> 209 | I11: 120 | J11: =H11*D11 -> 4180 | K11: =IFERROR(Medicine_Master!H11-TODAY(),"") -> 51 | L11: =IFERROR(IF(Medicine_Master!H11<TODAY(),"EXPIRED",IF(Medicine_Master!H11-TODAY()<30,"URGENT",IF(Medicine_Master!H11-TODAY()<60,"WARNING","OK"))),"OK") -> WARNING | M11: =IF(H11<I11,"YES","NO") -> NO | N11: =IFERROR(IF(H11<I11,MAX(I11-H11,ROUNDUP(SUMIF(Sales_Entry!D:D,A11,Sales_Entry!G:G)/90*30,0)),0),0) -> 0 | O11: =IFERROR(IF(SUMIF(Sales_Entry!C:C,">="&(TODAY()-60),Sales_Entry!G:G)=0,"Slow Moving","Active"),"Active") -> Active
A12: MED011 | B12: Aspirin 75mg | C12: Analgesics | D12: 8 | E12: 18 | F12: =IFERROR(SUMIF(Purchase_Entry!C:C,A12,Purchase_Entry!F:F),0) -> 0 | G12: =IFERROR(SUMIF(Sales_Entry!D:D,A12,Sales_Entry!G:G),0) -> 0 | H12: =F12-G12 -> 0 | I12: 150 | J12: =H12*D12 -> 0 | K12: =IFERROR(Medicine_Master!H12-TODAY(),"") -> 167 | L12: =IFERROR(IF(Medicine_Master!H12<TODAY(),"EXPIRED",IF(Medicine_Master!H12-TODAY()<30,"URGENT",IF(Medicine_Master!H12-TODAY()<60,"WARNING","OK"))),"OK") -> OK | M12: =IF(H12<I12,"YES","NO") -> YES | N12: =IFERROR(IF(H12<I12,MAX(I12-H12,ROUNDUP(SUMIF(Sales_Entry!D:D,A12,Sales_Entry!G:G)/90*30,0)),0),0) -> 150 | O12: =IFERROR(IF(SUMIF(Sales_Entry!C:C,">="&(TODAY()-60),Sales_Entry!G:G)=0,"Slow Moving","Active"),"Active") -> Active
A13: MED012 | B13: Tramadol 50mg | C13: Analgesics | D13: 46 | E13: 95 | F13: =IFERROR(SUMIF(Purchase_Entry!C:C,A13,Purchase_Entry!F:F),0) -> 436 | G13: =IFERROR(SUMIF(Sales_Entry!D:D,A13,Sales_Entry!G:G),0) -> 0 | H13: =F13-G13 -> 436 | I13: 70 | J13: =H13*D13 -> 20056 | K13: =IFERROR(Medicine_Master!H13-TODAY(),"") -> 689 | L13: =IFERROR(IF(Medicine_Master!H13<TODAY(),"EXPIRED",IF(Medicine_Master!H13-TODAY()<30,"URGENT",IF(Medicine_Master!H13-TODAY()<60,"WARNING","OK"))),"OK") -> OK | M13: =IF(H13<I13,"YES","NO") -> NO | N13: =IFERROR(IF(H13<I13,MAX(I13-H13,ROUNDUP(SUMIF(Sales_Entry!D:D,A13,Sales_Entry!G:G)/90*30,0)),0),0) -> 0 | O13: =IFERROR(IF(SUMIF(Sales_Entry!C:C,">="&(TODAY()-60),Sales_Entry!G:G)=0,"Slow Moving","Active"),"Active") -> Active
... A97: MED096 | B97: Tacrolimus Ointment | C97: Skin Care | D97: 210 | E97: 425 | F97: =IFERROR(SUMIF(Purchase_Entry!C:C,A97,Purchase_Entry!F:F),0) -> 210 | G97: =IFERROR(SUMIF(Sales_Entry!D:D,A97,Sales_Entry!G:G),0) -> 0 | H97: =F97-G97 -> 210 | I97: 25 | J97: =H97*D97 -> 44100 | K97: =IFERROR(Medicine_Master!H97-TODAY(),"") -> 477 | L97: =IFERROR(IF(Medicine_Master!H97<TODAY(),"EXPIRED",IF(Medicine_Master!H97-TODAY()<30,"URGENT",IF(Medicine_Master!H97-TODAY()<60,"WARNING","OK"))),"OK") -> OK | M97: =IF(H97<I97,"YES","NO") -> NO | N97: =IFERROR(IF(H97<I97,MAX(I97-H97,ROUNDUP(SUMIF(Sales_Entry!D:D,A97,Sales_Entry!G:G)/90*30,0)),0),0) -> 0 | O97: =IFERROR(IF(SUMIF(Sales_Entry!C:C,">="&(TODAY()-60),Sales_Entry!G:G)=0,"Slow Moving","Active"),"Active") -> Active

Sheet Expiry_Alert
A1: ⚠ EXPIRY ALERT REPORT ⚠
A2: Med_ID | B2: Medicine_Name | C2: Category | D2: Current_Stock | E2: Expiry_Date | F2: Days_Remaining | G2: Expiry_Status | H2: Cost_Price_PKR | I2: Financial_Risk_PKR
A3: MED001 | B3: Amoxicillin 500mg | C3: Antibiotics | D3: =IFERROR(SUMIF(Purchase_Entry!C:C,A3,Purchase_Entry!F:F)-SUMIF(Sales_Entry!D:D,A3,Sales_Entry!G:G),0) -> 927 | E3: 46090 | F3: =IFERROR(Medicine_Master!H2-TODAY(),"") -> 3 | G3: =IFERROR(IF(Medicine_Master!H2<TODAY(),"EXPIRED",IF(Medicine_Master!H2-TODAY()<30,"URGENT",IF(Medicine_Master!H2-TODAY()<60,"WARNING","OK"))),"OK") -> URGENT | H3: 22 | I3: =IFERROR(D3*H3,0) -> 20394
A4: MED002 | B4: Augmentin 625mg | C4: Antibiotics | D4: =IFERROR(SUMIF(Purchase_Entry!C:C,A4,Purchase_Entry!F:F)-SUMIF(Sales_Entry!D:D,A4,Sales_Entry!G:G),0) -> 493 | E4: 46386 | F4: =IFERROR(Medicine_Master!H3-TODAY(),"") -> 299 | G4: =IFERROR(IF(Medicine_Master!H3<TODAY(),"EXPIRED",IF(Medicine_Master!H3-TODAY()<30,"URGENT",IF(Medicine_Master!H3-TODAY()<60,"WARNING","OK"))),"OK") -> OK | H4: 110 | I4: =IFERROR(D4*H4,0) -> 54230
A5: MED003 | B5: Azithromycin 250mg | C5: Antibiotics | D5: =IFERROR(SUMIF(Purchase_Entry!C:C,A5,Purchase_Entry!F:F)-SUMIF(Sales_Entry!D:D,A5,Sales_Entry!G:G),0) -> 354 | E5: 46726 | F5: =IFERROR(Medicine_Master!H4-TODAY(),"") -> 639 | G5: =IFERROR(IF(Medicine_Master!H4<TODAY(),"EXPIRED",IF(Medicine_Master!H4-TODAY()<30,"URGENT",IF(Medicine_Master!H4-TODAY()<60,"WARNING","OK"))),"OK") -> OK | H5: 88 | I5: =IFERROR(D5*H5,0) -> 31152
A6: MED004 | B6: Ciprofloxacin 500mg | C6: Antibiotics | D6: =IFERROR(SUMIF(Purchase_Entry!C:C,A6,Purchase_Entry!F:F)-SUMIF(Sales_Entry!D:D,A6,Sales_Entry!G:G),0) -> 218 | E6: 46478 | F6: =IFERROR(Medicine_Master!H5-TODAY(),"") -> 391 | G6: =IFERROR(IF(Medicine_Master!H5<TODAY(),"EXPIRED",IF(Medicine_Master!H5-TODAY()<30,"URGENT",IF(Medicine_Master!H5-TODAY()<60,"WARNING","OK"))),"OK") -> OK | H6: 46 | I6: =IFERROR(D6*H6,0) -> 10028
A7: MED005 | B7: Metronidazole 400mg | C7: Antibiotics | D7: =IFERROR(SUMIF(Purchase_Entry!C:C,A7,Purchase_Entry!F:F)-SUMIF(Sales_Entry!D:D,A7,Sales_Entry!G:G),0) -> 65 | E7: 46278 | F7: =IFERROR(Medicine_Master!H6-TODAY(),"") -> 191 | G7: =IFERROR(IF(Medicine_Master!H6<TODAY(),"EXPIRED",IF(Medicine_Master!H6-TODAY()<30,"URGENT",IF(Medicine_Master!H6-TODAY()<60,"WARNING","OK"))),"OK") -> OK | H7: 17 | I7: =IFERROR(D7*H7,0) -> 1105
A8: MED006 | B8: Cephalexin 500mg | C8: Antibiotics | D8: =IFERROR(SUMIF(Purchase_Entry!C:C,A8,Purchase_Entry!F:F)-SUMIF(Sales_Entry!D:D,A8,Sales_Entry!G:G),0) -> 388 | E8: 46117 | F8: =IFERROR(Medicine_Master!H7-TODAY(),"") -> 30 | G8: =IFERROR(IF(Medicine_Master!H7<TODAY(),"EXPIRED",IF(Medicine_Master!H7-TODAY()<30,"URGENT",IF(Medicine_Master!H7-TODAY()<60,"WARNING","OK"))),"OK") -> WARNING | H8: 58 | I8: =IFERROR(D8*H8,0) -> 22504
A9: MED007 | B9: Doxycycline 100mg | C9: Antibiotics | D9: =IFERROR(SUMIF(Purchase_Entry!C:C,A9,Purchase_Entry!F:F)-SUMIF(Sales_Entry!D:D,A9,Sales_Entry!G:G),0) -> 0 | E9: 46713 | F9: =IFERROR(Medicine_Master!H8-TODAY(),"") -> 626 | G9: =IFERROR(IF(Medicine_Master!H8<TODAY(),"EXPIRED",IF(Medicine_Master!H8-TODAY()<30,"URGENT",IF(Medicine_Master!H8-TODAY()<60,"WARNING","OK"))),"OK") -> OK | H9: 41 | I9: =IFERROR(D9*H9,0) -> 0
A10: MED008 | B10: Paracetamol 500mg | C10: Analgesics | D10: =IFERROR(SUMIF(Purchase_Entry!C:C,A10,Purchase_Entry!F:F)-SUMIF(Sales_Entry!D:D,A10,Sales_Entry!G:G),0) -> 566 | E10: 46130 | F10: =IFERROR(Medicine_Master!H9-TODAY(),"") -> 43 | G10: =IFERROR(IF(Medicine_Master!H9<TODAY(),"EXPIRED",IF(Medicine_Master!H9-TODAY()<30,"URGENT",IF(Medicine_Master!H9-TODAY()<60,"WARNING","OK"))),"OK") -> WARNING | H10: 5 | I10: =IFERROR(D10*H10,0) -> 2830
A11: MED009 | B11: Ibuprofen 400mg | C11: Analgesics | D11: =IFERROR(SUMIF(Purchase_Entry!C:C,A11,Purchase_Entry!F:F)-SUMIF(Sales_Entry!D:D,A11,Sales_Entry!G:G),0) -> 433 | E11: 46063 | F11: =IFERROR(Medicine_Master!H10-TODAY(),"") -> -24 | G11: =IFERROR(IF(Medicine_Master!H10<TODAY(),"EXPIRED",IF(Medicine_Master!H10-TODAY()<30,"URGENT",IF(Medicine_Master!H10-TODAY()<60,"WARNING","OK"))),"OK") -> EXPIRED | H11: 13 | I11: =IFERROR(D11*H11,0) -> 5629
A12: MED010 | B12: Diclofenac 50mg | C12: Analgesics | D12: =IFERROR(SUMIF(Purchase_Entry!C:C,A12,Purchase_Entry!F:F)-SUMIF(Sales_Entry!D:D,A12,Sales_Entry!G:G),0) -> 209 | E12: 46138 | F12: =IFERROR(Medicine_Master!H11-TODAY(),"") -> 51 | G12: =IFERROR(IF(Medicine_Master!H11<TODAY(),"EXPIRED",IF(Medicine_Master!H11-TODAY()<30,"URGENT",IF(Medicine_Master!H11-TODAY()<60,"WARNING","OK"))),"OK") -> WARNING | H12: 20 | I12: =IFERROR(D12*H12,0) -> 4180
A13: MED011 | B13: Aspirin 75mg | C13: Analgesics | D13: =IFERROR(SUMIF(Purchase_Entry!C:C,A13,Purchase_Entry!F:F)-SUMIF(Sales_Entry!D:D,A13,Sales_Entry!G:G),0) -> 0 | E13: 46254 | F13: =IFERROR(Medicine_Master!H12-TODAY(),"") -> 167 | G13: =IFERROR(IF(Medicine_Master!H12<TODAY(),"EXPIRED",IF(Medicine_Master!H12-TODAY()<30,"URGENT",IF(Medicine_Master!H12-TODAY()<60,"WARNING","OK"))),"OK") -> OK | H13: 8 | I13: =IFERROR(D13*H13,0) -> 0
A14: MED012 | B14: Tramadol 50mg | C14: Analgesics | D14: =IFERROR(SUMIF(Purchase_Entry!C:C,A14,Purchase_Entry!F:F)-SUMIF(Sales_Entry!D:D,A14,Sales_Entry!G:G),0) -> 436 | E14: 46776 | F14: =IFERROR(Medicine_Master!H13-TODAY(),"") -> 689 | G14: =IFERROR(IF(Medicine_Master!H13<TODAY(),"EXPIRED",IF(Medicine_Master!H13-TODAY()<30,"URGENT",IF(Medicine_Master!H13-TODAY()<60,"WARNING","OK"))),"OK") -> OK | H14: 46 | I14: =IFERROR(D14*H14,0) -> 20056
... A98: MED096 | B98: Tacrolimus Ointment | C98: Skin Care | D98: =IFERROR(SUMIF(Purchase_Entry!C:C,A98,Purchase_Entry!F:F)-SUMIF(Sales_Entry!D:D,A98,Sales_Entry!G:G),0) -> 210 | E98: 46564 | F98: =IFERROR(Medicine_Master!H97-TODAY(),"") -> 477 | G98: =IFERROR(IF(Medicine_Master!H97<TODAY(),"EXPIRED",IF(Medicine_Master!H97-TODAY()<30,"URGENT",IF(Medicine_Master!H97-TODAY()<60,"WARNING","OK"))),"OK") -> OK | H98: 210 | I98: =IFERROR(D98*H98,0) -> 44100

Sheet Low_Stock_Alert
A1: 📦 LOW STOCK ALERT REPORT 📦
A2: Med_ID | B2: Medicine_Name | C2: Category | D2: Current_Stock | E2: Reorder_Level | F2: Shortage | G2: Suggested_Order | H2: Priority
A3: MED001 | B3: Amoxicillin 500mg | C3: Antibiotics | D3: =IFERROR(SUMIF(Purchase_Entry!C:C,A3,Purchase_Entry!F:F)-SUMIF(Sales_Entry!D:D,A3,Sales_Entry!G:G),0) -> 927 | E3: 100 | F3: =MAX(0,E3-D3) -> 0 | G3: =IFERROR(MAX(E3-D3,ROUNDUP(SUMIF(Sales_Entry!D:D,A3,Sales_Entry!G:G)/90*30,0)),0) -> 0 | H3: =IF(D3=0,"CRITICAL",IF(D3<E3/2,"HIGH",IF(D3<E3,"MEDIUM","OK"))) -> OK
A4: MED002 | B4: Augmentin 625mg | C4: Antibiotics | D4: =IFERROR(SUMIF(Purchase_Entry!C:C,A4,Purchase_Entry!F:F)-SUMIF(Sales_Entry!D:D,A4,Sales_Entry!G:G),0) -> 493 | E4: 50 | F4: =MAX(0,E4-D4) -> 0 | G4: =IFERROR(MAX(E4-D4,ROUNDUP(SUMIF(Sales_Entry!D:D,A4,Sales_Entry!G:G)/90*30,0)),0) -> 45 | H4: =IF(D4=0,"CRITICAL",IF(D4<E4/2,"HIGH",IF(D4<E4,"MEDIUM","OK"))) -> OK
A5: MED003 | B5: Azithromycin 250mg | C5: Antibiotics | D5: =IFERROR(SUMIF(Purchase_Entry!C:C,A5,Purchase_Entry!F:F)-SUMIF(Sales_Entry!D:D,A5,Sales_Entry!G:G),0) -> 354 | E5: 60 | F5: =MAX(0,E5-D5) -> 0 | G5: =IFERROR(MAX(E5-D5,ROUNDUP(SUMIF(Sales_Entry!D:D,A5,Sales_Entry!G:G)/90*30,0)),0) -> 31 | H5: =IF(D5=0,"CRITICAL",IF(D5<E5/2,"HIGH",IF(D5<E5,"MEDIUM","OK"))) -> OK
A6: MED004 | B6: Ciprofloxacin 500mg | C6: Antibiotics | D6: =IFERROR(SUMIF(Purchase_Entry!C:C,A6,Purchase_Entry!F:F)-SUMIF(Sales_Entry!D:D,A6,Sales_Entry!G:G),0) -> 218 | E6: 80 | F6: =MAX(0,E6-D6) -> 0 | G6: =IFERROR(MAX(E6-D6,ROUNDUP(SUMIF(Sales_Entry!D:D,A6,Sales_Entry!G:G)/90*30,0)),0) -> 30 | H6: =IF(D6=0,"CRITICAL",IF(D6<E6/2,"HIGH",IF(D6<E6,"MEDIUM","OK"))) -> OK
A7: MED005 | B7: Metronidazole 400mg | C7: Antibiotics | D7: =IFERROR(SUMIF(Purchase_Entry!C:C,A7,Purchase_Entry!F:F)-SUMIF(Sales_Entry!D:D,A7,Sales_Entry!G:G),0) -> 65 | E7: 100 | F7: =MAX(0,E7-D7) -> 35 | G7: =IFERROR(MAX(E7-D7,ROUNDUP(SUMIF(Sales_Entry!D:D,A7,Sales_Entry!G:G)/90*30,0)),0) -> 35 | H7: =IF(D7=0,"CRITICAL",IF(D7<E7/2,"HIGH",IF(D7<E7,"MEDIUM","OK"))) -> MEDIUM
A8: MED006 | B8: Cephalexin 500mg | C8: Antibiotics | D8: =IFERROR(SUMIF(Purchase_Entry!C:C,A8,Purchase_Entry!F:F)-SUMIF(Sales_Entry!D:D,A8,Sales_Entry!G:G),0) -> 388 | E8: 60 | F8: =MAX(0,E8-D8) -> 0 | G8: =IFERROR(MAX(E8-D8,ROUNDUP(SUMIF(Sales_Entry!D:D,A8,Sales_Entry!G:G)/90*30,0)),0) -> 0 | H8: =IF(D8=0,"CRITICAL",IF(D8<E8/2,"HIGH",IF(D8<E8,"MEDIUM","OK"))) -> OK
A9: MED007 | B9: Doxycycline 100mg | C9: Antibiotics | D9: =IFERROR(SUMIF(Purchase_Entry!C:C,A9,Purchase_Entry!F:F)-SUMIF(Sales_Entry!D:D,A9,Sales_Entry!G:G),0) -> 0 | E9: 80 | F9: =MAX(0,E9-D9) -> 80 | G9: =IFERROR(MAX(E9-D9,ROUNDUP(SUMIF(Sales_Entry!D:D,A9,Sales_Entry!G:G)/90*30,0)),0) -> 80 | H9: =IF(D9=0,"CRITICAL",IF(D9<E9/2,"HIGH",IF(D9<E9,"MEDIUM","OK"))) -> CRITICAL
A10: MED008 | B10: Paracetamol 500mg | C10: Analgesics | D10: =IFERROR(SUMIF(Purchase_Entry!C:C,A10,Purchase_Entry!F:F)-SUMIF(Sales_Entry!D:D,A10,Sales_Entry!G:G),0) -> 566 | E10: 200 | F10: =MAX(0,E10-D10) -> 0 | G10: =IFERROR(MAX(E10-D10,ROUNDUP(SUMIF(Sales_Entry!D:D,A10,Sales_Entry!G:G)/90*30,0)),0) -> 0 | H10: =IF(D10=0,"CRITICAL",IF(D10<E10/2,"HIGH",IF(D10<E10,"MEDIUM","OK"))) -> OK
A11: MED009 | B11: Ibuprofen 400mg | C11: Analgesics | D11: =IFERROR(SUMIF(Purchase_Entry!C:C,A11,Purchase_Entry!F:F)-SUMIF(Sales_Entry!D:D,A11,Sales_Entry!G:G),0) -> 433 | E11: 150 | F11: =MAX(0,E11-D11) -> 0 | G11: =IFERROR(MAX(E11-D11,ROUNDUP(SUMIF(Sales_Entry!D:D,A11,Sales_Entry!G:G)/90*30,0)),0) -> 2 | H11: =IF(D11=0,"CRITICAL",IF(D11<E11/2,"HIGH",IF(D11<E11,"MEDIUM","OK"))) -> OK
A12: MED010 | B12: Diclofenac 50mg | C12: Analgesics | D12: =IFERROR(SUMIF(Purchase_Entry!C:C,A12,Purchase_Entry!F:F)-SUMIF(Sales_Entry!D:D,A12,Sales_Entry!G:G),0) -> 209 | E12: 120 | F12: =MAX(0,E12-D12) -> 0 | G12: =IFERROR(MAX(E12-D12,ROUNDUP(SUMIF(Sales_Entry!D:D,A12,Sales_Entry!G:G)/90*30,0)),0) -> 3 | H12: =IF(D12=0,"CRITICAL",IF(D12<E12/2,"HIGH",IF(D12<E12,"MEDIUM","OK"))) -> OK
A13: MED011 | B13: Aspirin 75mg | C13: Analgesics | D13: =IFERROR(SUMIF(Purchase_Entry!C:C,A13,Purchase_Entry!F:F)-SUMIF(Sales_Entry!D:D,A13,Sales_Entry!G:G),0) -> 0 | E13: 150 | F13: =MAX(0,E13-D13) -> 150 | G13: =IFERROR(MAX(E13-D13,ROUNDUP(SUMIF(Sales_Entry!D:D,A13,Sales_Entry!G:G)/90*30,0)),0) -> 150 | H13: =IF(D13=0,"CRITICAL",IF(D13<E13/2,"HIGH",IF(D13<E13,"MEDIUM","OK"))) -> CRITICAL
A14: MED012 | B14: Tramadol 50mg | C14: Analgesics | D14: =IFERROR(SUMIF(Purchase_Entry!C:C,A14,Purchase_Entry!F:F)-SUMIF(Sales_Entry!D:D,A14,Sales_Entry!G:G),0) -> 436 | E14: 70 | F14: =MAX(0,E14-D14) -> 0 | G14: =IFERROR(MAX(E14-D14,ROUNDUP(SUMIF(Sales_Entry!D:D,A14,Sales_Entry!G:G)/90*30,0)),0) -> 0 | H14: =IF(D14=0,"CRITICAL",IF(D14<E14/2,"HIGH",IF(D14<E14,"MEDIUM","OK"))) -> OK
... A98: MED096 | B98: Tacrolimus Ointment | C98: Skin Care | D98: =IFERROR(SUMIF(Purchase_Entry!C:C,A98,Purchase_Entry!F:F)-SUMIF(Sales_Entry!D:D,A98,Sales_Entry!G:G),0) -> 210 | E98: 25 | F98: =MAX(0,E98-D98) -> 0 | G98: =IFERROR(MAX(E98-D98,ROUNDUP(SUMIF(Sales_Entry!D:D,A98,Sales_Entry!G:G)/90*30,0)),0) -> 0 | H98: =IF(D98=0,"CRITICAL",IF(D98<E98/2,"HIGH",IF(D98<E98,"MEDIUM","OK"))) -> OK

Sheet Credit_Report
A1: 💳 CREDIT CUSTOMER REPORT 💳
A2: Sale_ID | B2: Date | C2: Customer_Name | D2: Medicine_Name | E2: Total_Amount_PKR | F2: Amount_Paid_PKR | G2: Balance_Due_PKR | H2: Days_Outstanding | I2: Aging_Category | J2: Collection_Status
A3: SAL0015 | B3: 46039 | C3: Nadia Hussain | D3: Benzoyl Peroxide | E3: 5510 | F3: 2755 | G3: 2755 | H3: 46 | I3: 31-60 Days | J3: Overdue
A4: SAL0016 | B4: 46075 | C4: Tariq Mahmood | D4: Iron+Folic Acid | E4: 1260 | F4: 630 | G4: 630 | H4: 10 | I4: 0-30 Days | J4: Current
A5: SAL0017 | B5: 46049 | C5: Ayesha Siddiqui | D5: Levofloxacin 500mg | E5: 4070 | F5: 0 | G5: 4070 | H5: 36 | I5: 31-60 Days | J5: Overdue
A6: SAL0023 | B6: 46077 | C6: Hina Shah | D6: Lisinopril 10mg | E6: 1395 | F6: 0 | G6: 1395 | H6: 8 | I6: 0-30 Days | J6: Current
A7: SAL0024 | B7: 46028 | C7: Imran Chaudhry | D7: Montelukast 10mg | E7: 3145 | F7: 1572 | G7: 1573 | H7: 57 | I7: 31-60 Days | J7: Overdue
A8: SAL0027 | B8: 46069 | C8: Imran Chaudhry | D8: Paracetamol 500mg | E8: 168 | F8: 0 | G8: 168 | H8: 16 | I8: 0-30 Days | J8: Current
A9: SAL0031 | B9: 46056 | C9: Usman Ali | D9: Povidone Iodine | E9: 6380 | F9: 0 | G9: 6380 | H9: 29 | I9: 0-30 Days | J9: Current
A10: SAL0033 | B10: 46062 | C10: Hina Shah | D10: Augmentin 625mg | E10: 7040 | F10: 3520 | G10: 3520 | H10: 23 | I10: 0-30 Days | J10: Current
A11: SAL0036 | B11: 46002 | C11: Asif Mirza | D11: Ipratropium | E11: 9405 | F11: 0 | G11: 9405 | H11: 83 | I11: 60+ Days | J11: Overdue
A12: SAL0037 | B12: 46035 | C12: Imran Chaudhry | D12: Ciprofloxacin 500mg | E12: 4180 | F12: 2090 | G12: 2090 | H12: 50 | I12: 31-60 Days | J12: Overdue
A13: SAL0042 | B13: 46007 | C13: Usman Ali | D13: Piroxicam 20mg | E13: 385 | F13: 0 | G13: 385 | H13: 78 | I13: 60+ Days | J13: Overdue
A14: SAL0045 | B14: 46026 | C14: Mehwish Qureshi | D14: Ranitidine 150mg | E14: 304 | F14: 152 | G14: 152 | H14: 59 | I14: 31-60 Days | J14: Overdue
... A27: SAL0096 | B27: 46072 | C27: Zubair Ahmed | D27: Pantoprazole 40mg | E27: 1275 | F27: 0 | G27: 1275 | H27: 13 | I27: 0-30 Days | J27: Current

Sheet Profit_Report
A1: 📊 PROFIT ANALYSIS REPORT 📊
A2: Med_ID | B2: Medicine_Name | C2: Category | D2: Total_Qty_Sold | E2: Total_Revenue_PKR | F2: Total_Cost_PKR | G2: Gross_Profit_PKR | H2: Margin_%
A3: MED001 | B3: Amoxicillin 500mg | C3: Antibiotics | D3: =IFERROR(SUMIF(Sales_Entry!D:D,A3,Sales_Entry!G:G),0) -> 0 | E3: =IFERROR(SUMIF(Sales_Entry!D:D,A3,Sales_Entry!I:I),0) -> 0 | F3: =IFERROR(SUMIF(Sales_Entry!D:D,A3,Sales_Entry!K:K),0) -> 0 | G3: =E3-F3 -> 0 | H3: =IFERROR(G3/E3,0) -> 0
A4: MED002 | B4: Augmentin 625mg | C4: Antibiotics | D4: =IFERROR(SUMIF(Sales_Entry!D:D,A4,Sales_Entry!G:G),0) -> 135 | E4: =IFERROR(SUMIF(Sales_Entry!D:D,A4,Sales_Entry!I:I),0) -> 29700 | F4: =IFERROR(SUMIF(Sales_Entry!D:D,A4,Sales_Entry!K:K),0) -> 14850 | G4: =E4-F4 -> 14850 | H4: =IFERROR(G4/E4,0) -> 0.5
A5: MED003 | B5: Azithromycin 250mg | C5: Antibiotics | D5: =IFERROR(SUMIF(Sales_Entry!D:D,A5,Sales_Entry!G:G),0) -> 93 | E5: =IFERROR(SUMIF(Sales_Entry!D:D,A5,Sales_Entry!I:I),0) -> 16740 | F5: =IFERROR(SUMIF(Sales_Entry!D:D,A5,Sales_Entry!K:K),0) -> 8184 | G5: =E5-F5 -> 8556 | H5: =IFERROR(G5/E5,0) -> 0.51111111
A6: MED004 | B6: Ciprofloxacin 500mg | C6: Antibiotics | D6: =IFERROR(SUMIF(Sales_Entry!D:D,A6,Sales_Entry!G:G),0) -> 88 | E6: =IFERROR(SUMIF(Sales_Entry!D:D,A6,Sales_Entry!I:I),0) -> 8360 | F6: =IFERROR(SUMIF(Sales_Entry!D:D,A6,Sales_Entry!K:K),0) -> 4048 | G6: =E6-F6 -> 4312 | H6: =IFERROR(G6/E6,0) -> 0.51578947
A7: MED005 | B7: Metronidazole 400mg | C7: Antibiotics | D7: =IFERROR(SUMIF(Sales_Entry!D:D,A7,Sales_Entry!G:G),0) -> 0 | E7: =IFERROR(SUMIF(Sales_Entry!D:D,A7,Sales_Entry!I:I),0) -> 0 | F7: =IFERROR(SUMIF(Sales_Entry!D:D,A7,Sales_Entry!K:K),0) -> 0 | G7: =E7-F7 -> 0 | H7: =IFERROR(G7/E7,0) -> 0
A8: MED006 | B8: Cephalexin 500mg | C8: Antibiotics | D8: =IFERROR(SUMIF(Sales_Entry!D:D,A8,Sales_Entry!G:G),0) -> 0 | E8: =IFERROR(SUMIF(Sales_Entry!D:D,A8,Sales_Entry!I:I),0) -> 0 | F8: =IFERROR(SUMIF(Sales_Entry!D:D,A8,Sales_Entry!K:K),0) -> 0 | G8: =E8-F8 -> 0 | H8: =IFERROR(G8/E8,0) -> 0
A9: MED007 | B9: Doxycycline 100mg | C9: Antibiotics | D9: =IFERROR(SUMIF(Sales_Entry!D:D,A9,Sales_Entry!G:G),0) -> 0 | E9: =IFERROR(SUMIF(Sales_Entry!D:D,A9,Sales_Entry!I:I),0) -> 0 | F9: =IFERROR(SUMIF(Sales_Entry!D:D,A9,Sales_Entry!K:K),0) -> 0 | G9: =E9-F9 -> 0 | H9: =IFERROR(G9/E9,0) -> 0
A10: MED008 | B10: Paracetamol 500mg | C10: Analgesics | D10: =IFERROR(SUMIF(Sales_Entry!D:D,A10,Sales_Entry!G:G),0) -> 0 | E10: =IFERROR(SUMIF(Sales_Entry!D:D,A10,Sales_Entry!I:I),0) -> 0 | F10: =IFERROR(SUMIF(Sales_Entry!D:D,A10,Sales_Entry!K:K),0) -> 0 | G10: =E10-F10 -> 0 | H10: =IFERROR(G10/E10,0) -> 0
A11: MED009 | B11: Ibuprofen 400mg | C11: Analgesics | D11: =IFERROR(SUMIF(Sales_Entry!D:D,A11,Sales_Entry!G:G),0) -> 6 | E11: =IFERROR(SUMIF(Sales_Entry!D:D,A11,Sales_Entry!I:I),0) -> 168 | F11: =IFERROR(SUMIF(Sales_Entry!D:D,A11,Sales_Entry!K:K),0) -> 78 | G11: =E11-F11 -> 90 | H11: =IFERROR(G11/E11,0) -> 0.53571429
A12: MED010 | B12: Diclofenac 50mg | C12: Analgesics | D12: =IFERROR(SUMIF(Sales_Entry!D:D,A12,Sales_Entry!G:G),0) -> 8 | E12: =IFERROR(SUMIF(Sales_Entry!D:D,A12,Sales_Entry!I:I),0) -> 336 | F12: =IFERROR(SUMIF(Sales_Entry!D:D,A12,Sales_Entry!K:K),0) -> 160 | G12: =E12-F12 -> 176 | H12: =IFERROR(G12/E12,0) -> 0.52380952
A13: MED011 | B13: Aspirin 75mg | C13: Analgesics | D13: =IFERROR(SUMIF(Sales_Entry!D:D,A13,Sales_Entry!G:G),0) -> 0 | E13: =IFERROR(SUMIF(Sales_Entry!D:D,A13,Sales_Entry!I:I),0) -> 0 | F13: =IFERROR(SUMIF(Sales_Entry!D:D,A13,Sales_Entry!K:K),0) -> 0 | G13: =E13-F13 -> 0 | H13: =IFERROR(G13/E13,0) -> 0
A14: MED012 | B14: Tramadol 50mg | C14: Analgesics | D14: =IFERROR(SUMIF(Sales_Entry!D:D,A14,Sales_Entry!G:G),0) -> 0 | E14: =IFERROR(SUMIF(Sales_Entry!D:D,A14,Sales_Entry!I:I),0) -> 0 | F14: =IFERROR(SUMIF(Sales_Entry!D:D,A14,Sales_Entry!K:K),0) -> 0 | G14: =E14-F14 -> 0 | H14: =IFERROR(G14/E14,0) -> 0
... A98: MED096 | B98: Tacrolimus Ointment | C98: Skin Care | D98: =IFERROR(SUMIF(Sales_Entry!D:D,A98,Sales_Entry!G:G),0) -> 0 | E98: =IFERROR(SUMIF(Sales_Entry!D:D,A98,Sales_Entry!I:I),0) -> 0 | F98: =IFERROR(SUMIF(Sales_Entry!D:D,A98,Sales_Entry!K:K),0) -> 0 | G98: =E98-F98 -> 0 | H98: =IFERROR(G98/E98,0) -> 0
